scippy/__init__.py
scippy/conftest.py
scippy/examples/examples.py
scippy/source/Agilent33210A.py
scippy/source/Keithley2400.py
scippy/source/MCP3561.py
scippy/source/SCPIDevice.py
scippy/source/motor_controller.py
scippy/source/twos_postprocessing.py
scippy/test/__init__.py
scippy/test/conftest.py
scippy/test/shorthand.py
scippy/test/test_adc_processing.py
scippy/test/test_adc_properties.py
scippy/test/test_agilent.py
scippy/test/test_keithley.py
scippy/test/test_mcp.py
scippy/test/test_mcp_measurement.py
scippy/test/test_mcp_motor.py
scippy/test/test_scpi_core.py
scippy-0.1.31.dist-info/LICENSE.txt
scippy-0.1.31.dist-info/METADATA
scippy-0.1.31.dist-info/WHEEL
scippy-0.1.31.dist-info/top_level.txt
scippy-0.1.31.dist-info/RECORD
